{
  "states": {
    "Missouri": {
      "counted": {
        "republican": 792514,
        "democrat": 586760
      },
      "exit_poll": {
        "republican": 0,
        "democrat": 0
      },
      "reporting": 45.66,
      "called": true
    },
    "New York": {
      "counted": {
        "republican": 3149202,
        "democrat": 4028353
      },
      "exit_poll": {
        "republican": 0,
        "democrat": 0
      },
      "reporting": 86.35,
      "called": true
    },
    "Alaska": {
      "counted": {
        "republican": 0,
        "democrat": 0
      },
      "exit_poll": {
        "republican": 0,
        "democrat": 0
      },
      "reporting": 0,
      "called": false
    },
    "Illinois": {
      "counted": {
        "republican": 2128113,
        "democrat": 2511120
      },
      "exit_poll": {
        "republican": 0,
        "democrat": 0
      },
      "reporting": 82.42,
      "called": true
    },
    "South Carolina": {
      "counted": {
        "republican": 1316984,
        "democrat": 904824
      },
      "exit_poll": {
        "republican": 0,
        "democrat": 0
      },
      "reporting": 93.14,
      "called": true
    },
    "Virginia": {
      "counted": {
        "republican": 1701963,
        "democrat": 1780820
      },
      "exit_poll": {
        "republican": 0,
        "democrat": 0
      },
      "reporting": 99.0,
      "called": true
    },
    "Washington": {
      "counted": {
        "republican": 65454,
        "democrat": 48922
      },
      "exit_poll": {
        "republican": 0,
        "democrat": 0
      },
      "reporting": 2.85,
      "called": false
    },
    "Vermont": {
      "counted": {
        "republican": 110314,
        "democrat": 220509
      },
      "exit_poll": {
        "republican": 0,
        "democrat": 0
      },
      "reporting": 98.39,
      "called": true
    },
    "South Dakota": {
      "counted": {
        "republican": 63104,
        "democrat": 28675
      },
      "exit_poll": {
        "republican": 0,
        "democrat": 0
      },
      "reporting": 23.0,
      "called": true
    },
    "Georgia": {
      "counted": {
        "republican": 2528685,
        "democrat": 2397583
      },
      "exit_poll": {
        "republican": 0,
        "democrat": 0
      },
      "reporting": 92.88,
      "called": true
    },
    "Connecticut": {
      "counted": {
        "republican": 126426,
        "democrat": 142850
      },
      "exit_poll": {
        "republican": 0,
        "democrat": 0
      },
      "reporting": 15.21,
      "called": true
    },
    "Alabama": {
      "counted": {
        "republican": 1013261,
        "democrat": 470662
      },
      "exit_poll": {
        "republican": 0,
        "democrat": 0
      },
      "reporting": 0,
      "called": false
    },
    "New Hampshire": {
      "counted": {
        "republican": 199395,
        "democrat": 227650
      },
      "exit_poll": {
        "republican": 0,
        "democrat": 0
      },
      "reporting": 59.87,
      "called": true
    },
    "Oklahoma": {
      "counted": {
        "republican": 1027198,
        "democrat": 495018
      },
      "exit_poll": {
        "republican": 0,
        "democrat": 0
      },
      "reporting": 96.72,
      "called": true
    },
    "Colorado": {
      "counted": {
        "republican": 889424,
        "democrat": 1132427
      },
      "exit_poll": {
        "republican": 0,
        "democrat": 0
      },
      "reporting": 62.07,
      "called": true
    },
    "Ohio": {
      "counted": {
        "republican": 2937621,
        "democrat": 2295339
      },
      "exit_poll": {
        "republican": 0,
        "democrat": 0
      },
      "reporting": 87.43,
      "called": true
    },
    "Maine": {
      "counted": {
        "republican": 24722,
        "democrat": 22744
      },
      "exit_poll": {
        "republican": 0,
        "democrat": 0
      },
      "reporting": 6.12,
      "called": false
    },
    "Mississippi": {
      "counted": {
        "republican": 525853,
        "democrat": 332379
      },
      "exit_poll": {
        "republican": 0,
        "democrat": 0
      },
      "reporting": 70.76,
      "called": true
    },
    "Utah": {
      "counted": {
        "republican": 0,
        "democrat": 0
      },
      "exit_poll": {
        "republican": 0,
        "democrat": 0
      },
      "reporting": 0.0,
      "called": true
    },
    "Delaware": {
      "counted": {
        "republican": 212546,
        "democrat": 285368
      },
      "exit_poll": {
        "republican": 0,
        "democrat": 0
      },
      "reporting": 92.76,
      "called": true
    },
    "Indiana": {
      "counted": {
        "republican": 1411090,
        "democrat": 942441
      },
      "exit_poll": {
        "republican": 0,
        "democrat": 0
      },
      "reporting": 79.58,
      "called": true
    },
    "Arkansas": {
      "counted": {
        "republican": 498087,
        "democrat": 275962
      },
      "exit_poll": {
        "republican": 0,
        "democrat": 0
      },
      "reporting": 67.5,
      "called": true
    },
    "Iowa": {
      "counted": {
        "republican": 508744,
        "democrat": 393941
      },
      "exit_poll": {
        "republican": 0,
        "democrat": 0
      },
      "reporting": 53.93,
      "called": true
    },
    "New Jersey": {
      "counted": {
        "republican": 1566657,
        "democrat": 1765851
      },
      "exit_poll": {
        "republican": 0,
        "democrat": 0
      },
      "reporting": 72.67,
      "called": false
    },
    "Wisconsin": {
      "counted": {
        "republican": 1077875,
        "democrat": 1026868
      },
      "exit_poll": {
        "republican": 0,
        "democrat": 0
      },
      "reporting": 65.6,
      "called": false
    },
    "Michigan": {
      "counted": {
        "republican": 875526,
        "democrat": 934047
      },
      "exit_poll": {
        "republican": 0,
        "democrat": 0
      },
      "reporting": 8.6,
      "called": false
    },
    "Arizona": {
      "counted": {
        "republican": 904351,
        "democrat": 901995
      },
      "exit_poll": {
        "republican": 0,
        "democrat": 0
      },
      "reporting": 54.46,
      "called": false
    },
    "Massachusetts": {
      "counted": {
        "republican": 513810,
        "democrat": 899799
      },
      "exit_poll": {
        "republican": 0,
        "democrat": 0
      },
      "reporting": 40.99,
      "called": true
    },
    "North Carolina": {
      "counted": {
        "republican": 2569207,
        "democrat": 2432590
      },
      "exit_poll": {
        "republican": 0,
        "democrat": 0
      },
      "reporting": 87.58,
      "called": true
    },
    "Montana": {
      "counted": {
        "republican": 20496,
        "democrat": 12299
      },
      "exit_poll": {
        "republican": 0,
        "democrat": 0
      },
      "reporting": 5.84,
      "called": true
    },
    "District of Columbia": {
      "counted": {
        "republican": 0,
        "democrat": 0
      },
      "exit_poll": {
        "republican": 0,
        "democrat": 0
      },
      "reporting": 0.0,
      "called": true
    },
    "Wyoming": {
      "counted": {
        "republican": 22742,
        "democrat": 4845
      },
      "exit_poll": {
        "republican": 0,
        "democrat": 0
      },
      "reporting": 10.58,
      "called": true
    },
    "Minnesota": {
      "counted": {
        "republican": 0,
        "democrat": 0
      },
      "exit_poll": {
        "republican": 0,
        "democrat": 0
      },
      "reporting": 0.0,
      "called": false
    },
    "Florida": {
      "counted": {
        "republican": 6072393,
        "democrat": 4629964
      },
      "exit_poll": {
        "republican": 0,
        "democrat": 0
      },
      "reporting": 99.0,
      "called": true
    },
    "Kentucky": {
      "counted": {
        "republican": 1329617,
        "democrat": 699673
      },
      "exit_poll": {
        "republican": 0,
        "democrat": 0
      },
      "reporting": 98.93,
      "called": true
    },
    "North Dakota": {
      "counted": {
        "republican": 148322,
        "democrat": 58583
      },
      "exit_poll": {
        "republican": 0,
        "democrat": 0
      },
      "reporting": 58.91,
      "called": true
    },
    "Louisiana": {
      "counted": {
        "republican": 1131108,
        "democrat": 653641
      },
      "exit_poll": {
        "republican": 0,
        "democrat": 0
      },
      "reporting": 91.01,
      "called": true
    },
    "Maryland": {
      "counted": {
        "republican": 582620,
        "democrat": 1167537
      },
      "exit_poll": {
        "republican": 0,
        "democrat": 0
      },
      "reporting": 57.96,
      "called": true
    },
    "Texas": {
      "counted": {
        "republican": 5329604,
        "democrat": 4005604
      },
      "exit_poll": {
        "republican": 0,
        "democrat": 0
      },
      "reporting": 78.93,
      "called": true
    },
    "Hawaii": {
      "counted": {
        "republican": 0,
        "democrat": 0
      },
      "exit_poll": {
        "republican": 0,
        "democrat": 0
      },
      "reporting": 0.0,
      "called": false
    },
    "Rhode Island": {
      "counted": {
        "republican": 196755,
        "democrat": 235778
      },
      "exit_poll": {
        "republican": 0,
        "democrat": 0
      },
      "reporting": 90.88,
      "called": true
    },
    "Kansas": {
      "counted": {
        "republican": 460410,
        "democrat": 384552
      },
      "exit_poll": {
        "republican": 0,
        "democrat": 0
      },
      "reporting": 65.02,
      "called": true
    },
    "Pennsylvania": {
      "counted": {
        "republican": 2706297,
        "democrat": 2537310
      },
      "exit_poll": {
        "republican": 0,
        "democrat": 0
      },
      "reporting": 74.05,
      "called": false
    },
    "Nebraska": {
      "counted": {
        "republican": 248175,
        "democrat": 221077
      },
      "exit_poll": {
        "republican": 0,
        "democrat": 0
      },
      "reporting": 48.75,
      "called": true
    },
    "Tennessee": {
      "counted": {
        "republican": 1886009,
        "democrat": 980202
      },
      "exit_poll": {
        "republican": 0,
        "democrat": 0
      },
      "reporting": 98.62,
      "called": true
    },
    "Idaho": {
      "counted": {
        "republican": 61963,
        "democrat": 55326
      },
      "exit_poll": {
        "republican": 0,
        "democrat": 0
      },
      "reporting": 13.29,
      "called": true
    },
    "Oregon": {
      "counted": {
        "republican": 157650,
        "democrat": 161953
      },
      "exit_poll": {
        "republican": 0,
        "democrat": 0
      },
      "reporting": 13.75,
      "called": false
    },
    "Nevada": {
      "counted": {
        "republican": 0,
        "democrat": 0
      },
      "exit_poll": {
        "republican": 0,
        "democrat": 0
      },
      "reporting": 0.0,
      "called": false
    },
    "California": {
      "counted": {
        "republican": 224508,
        "democrat": 435103
      },
      "exit_poll": {
        "republican": 0,
        "democrat": 0
      },
      "reporting": 4.03,
      "called": true
    },
    "West Virginia": {
      "counted": {
        "republican": 318208,
        "democrat": 118289
      },
      "exit_poll": {
        "republican": 0,
        "democrat": 0
      },
      "reporting": 58.59,
      "called": true
    },
    "New Mexico": {
      "counted": {
        "republican": 278375,
        "democrat": 330180
      },
      "exit_poll": {
        "republican": 0,
        "democrat": 0
      },
      "reporting": 65.86,
      "called": false
    }
  }
}